ipachecker/IPAChecker.py
ipachecker/__init__.py
ipachecker/__main__.py
ipachecker/utils.py
ipachecker-1.0.3.dist-info/licenses/LICENSE
ipachecker-1.0.3.dist-info/METADATA
ipachecker-1.0.3.dist-info/WHEEL
ipachecker-1.0.3.dist-info/entry_points.txt
ipachecker-1.0.3.dist-info/top_level.txt
ipachecker-1.0.3.dist-info/RECORD
