Metadata-Version: 2.4
Name: ipachecker
Version: 1.0.3
Summary: A python tool for analyzing .ipa files
Home-page: https://github.com/Andres9890/ipachecker
Author: Andres99
License:                     GNU GENERAL PUBLIC LICENSE
Project-URL: homepage, https://github.com/Andres9890/ipachecker
Project-URL: repository, https://github.com/Andres9890/ipachecker.git
Project-URL: issues, https://github.com/Andres9890/ipachecker/issues
Keywords: ios,ipa,analysis,metadata,encryption,mobile,app
Classifier: Development Status :: 4 - Beta
Classifier: Environment :: Console
Classifier: Intended Audience :: Developers
Classifier: Operating System :: OS Independent
Classifier: Programming Language :: Python :: 3 :: Only
Classifier: Programming Language :: Python :: 3.8
Classifier: Programming Language :: Python :: 3.9
Classifier: Programming Language :: Python :: 3.10
Classifier: Programming Language :: Python :: 3.11
Classifier: Programming Language :: Python :: 3.12
Classifier: Programming Language :: Python :: Implementation :: CPython
Classifier: Topic :: Software Development :: Libraries :: Python Modules
Classifier: Topic :: System :: Archiving
Classifier: Topic :: Utilities
Requires-Python: >=3.8
License-File: LICENSE
Requires-Dist: docopt-ng>=0.9.0
Requires-Dist: rich>=14.1.0
Requires-Dist: macholib>=1.16.3
Dynamic: home-page
Dynamic: license-file
Dynamic: requires-python
